meow_package/__init__.py
meow_package/banque.py
meow_package-0.1.1.dist-info/WHEEL
meow_package-0.1.1.dist-info/entry_points.txt
meow_package-0.1.1.dist-info/METADATA
meow_package-0.1.1.dist-info/RECORD
